delphi_epidata/__init__.py
delphi_epidata/delphi_epidata.py
delphi_epidata-4.1.25.dist-info/LICENSE
delphi_epidata-4.1.25.dist-info/METADATA
delphi_epidata-4.1.25.dist-info/WHEEL
delphi_epidata-4.1.25.dist-info/top_level.txt
delphi_epidata-4.1.25.dist-info/RECORD
