Metadata-Version: 2.1
Name: delphi_epidata
Version: 4.1.25
Summary: A programmatic interface to Delphi's Epidata API.
Author-email: David Farrow <dfarrow0@gmail.com>
Maintainer-email: Delphi Support <delphi-support+pypi@andrew.cmu.edu>
License: The MIT License (MIT)
Project-URL: Homepage, https://github.com/cmu-delphi/delphi-epidata
Project-URL: Changelog, https://github.com/cmu-delphi/delphi-epidata/blob/main/src/client/packaging/pypi/CHANGELOG.md
Classifier: License :: OSI Approved :: MIT License
Classifier: Programming Language :: Python
Classifier: Programming Language :: Python :: 2
Classifier: Programming Language :: Python :: 3
Classifier: Operating System :: OS Independent
Classifier: Intended Audience :: Science/Research
Classifier: Natural Language :: English
Classifier: Topic :: Scientific/Engineering :: Bio-Informatics
License-File: LICENSE
Requires-Dist: aiohttp
Requires-Dist: requests >=2.7.0
Requires-Dist: tenacity
